{
	"0": "papa",
	"1": "tipa",
	"2": "kupa",
	"3": "sepa",
	"4": "mopa",
	"5": "nata",
	"6": "lita",
	"7": "puta",
	"8": "teta",
	"9": "kota",
	"10": "saka",
	"11": "mika",
	"12": "nuka",
	"13": "leka",
	"14": "poka",
	"15": "tasa",
	"16": "kisa",
	"17": "susa",
	"18": "mesa",
	"19": "nosa",
	"20": "lama",
	"21": "pima",
	"22": "tuma",
	"23": "kema",
	"24": "soma",
	"25": "mana",
	"26": "nina",
	"27": "luna",
	"28": "pena",
	"29": "tona",
	"30": "kala",
	"31": "sila",
	"32": "mula",
	"33": "nela",
	"34": "lola",
	"35": "papi",
	"36": "tipi",
	"37": "kupi",
	"38": "sepi",
	"39": "mopi",
	"40": "nati",
	"41": "liti",
	"42": "puti",
	"43": "teti",
	"44": "koti",
	"45": "saki",
	"46": "miki",
	"47": "nuki",
	"48": "leki",
	"49": "poki",
	"50": "tasi",
	"51": "kisi",
	"52": "susi",
	"53": "mesi",
	"54": "nosi",
	"55": "lami",
	"56": "pimi",
	"57": "tumi",
	"58": "kemi",
	"59": "somi",
	"60": "mani",
	"61": "nini",
	"62": "luni",
	"63": "peni",
	"64": "toni",
	"65": "kali",
	"66": "sili",
	"67": "muli",
	"68": "neli",
	"69": "loli",
	"70": "papu",
	"71": "tipu",
	"72": "kupu",
	"73": "sepu",
	"74": "mopu",
	"75": "natu",
	"76": "litu",
	"77": "putu",
	"78": "tetu",
	"79": "kotu",
	"80": "saku",
	"81": "miku",
	"82": "nuku",
	"83": "leku",
	"84": "poku",
	"85": "tasu",
	"86": "kisu",
	"87": "susu",
	"88": "mesu",
	"89": "nosu",
	"90": "lamu",
	"91": "pimu",
	"92": "tumu",
	"93": "kemu",
	"94": "somu",
	"95": "manu",
	"96": "ninu",
	"97": "lunu",
	"98": "penu",
	"99": "tonu",
	"100": "kalu",
	"101": "silu",
	"102": "mulu",
	"103": "nelu",
	"104": "lolu",
	"105": "pape",
	"106": "tipe",
	"107": "kupe",
	"108": "sepe",
	"109": "mope",
	"110": "nate",
	"111": "lite",
	"112": "pute",
	"113": "tete",
	"114": "kote",
	"115": "sake",
	"116": "mike",
	"117": "nuke",
	"118": "leke",
	"119": "poke",
	"120": "tase",
	"121": "kise",
	"122": "suse",
	"123": "mese",
	"124": "nose",
	"125": "lame",
	"126": "pime",
	"127": "tume",
	"128": "keme",
	"129": "some",
	"130": "mane",
	"131": "nine",
	"132": "lune",
	"133": "pene",
	"134": "tone",
	"135": "kale",
	"136": "sile",
	"137": "mule",
	"138": "nele",
	"139": "lole",
	"140": "papo",
	"141": "tipo",
	"142": "kupo",
	"143": "sepo",
	"144": "mopo",
	"145": "nato",
	"146": "lito",
	"147": "puto",
	"148": "teto",
	"149": "koto",
	"150": "sako",
	"151": "miko",
	"152": "nuko",
	"153": "leko",
	"154": "poko",
	"155": "taso",
	"156": "kiso",
	"157": "suso",
	"158": "meso",
	"159": "noso",
	"160": "lamo",
	"161": "pimo",
	"162": "tumo",
	"163": "kemo",
	"164": "somo",
	"165": "mano",
	"166": "nino",
	"167": "luno",
	"168": "peno",
	"169": "tono",
	"170": "kalo",
	"171": "silo",
	"172": "mulo",
	"173": "nelo",
	"174": "lolo"
}